agpm.py
agpm-2.1.1.dist-info/licenses/LICENCE
agpm-2.1.1.dist-info/METADATA
agpm-2.1.1.dist-info/WHEEL
agpm-2.1.1.dist-info/entry_points.txt
agpm-2.1.1.dist-info/top_level.txt
agpm-2.1.1.dist-info/RECORD
