Metadata-Version: 2.4
Name: agpm
Version: 2.1.1
Summary: A package manager made in python to download EyeScary Development projects
Author: EyeScary Development
License:            DO WHAT THE FUCK YOU WANT TO PUBLIC LICENSE
License-File: LICENCE
Requires-Dist: requests
Dynamic: license-file
